README
setup.py
finitd/OrderedDict.py
finitd/__init__.py
finitd/commands.py
finitd/compat.py
finitd/conf.py
finitd/main.py
finitd/util.py
finitd.egg-info/PKG-INFO
finitd.egg-info/SOURCES.txt
finitd.egg-info/dependency_links.txt
finitd.egg-info/entry_points.txt
finitd.egg-info/requires.txt
finitd.egg-info/top_level.txt
finitd/test/__init__.py
finitd/test/test_conf.py
finitd/test/test_finitd.py
finitd/test/test_util.py