Metadata-Version: 1.0
Name: finitd
Version: 0.4
Summary: Simple init.d script replacement with support for daemonization,
Home-page: http://sourceforge.net/projects/finitd
Author: Jeremy Fincher
Author-email: jemfinch@finchers.us
License: BSD
Keywords: init.d daemon babysitting monitoring
Platform: UNKNOWN
